django_svelte_married/__init__.py
django_svelte_married/context_processors.py
django_svelte_married/js/exported.js
django_svelte_married/js/main.js
django_svelte_married/js/renderer.js
django_svelte_married/management/__init__.py
django_svelte_married/management/commands/__init__.py
django_svelte_married/management/commands/installsvelte.py
django_svelte_married/management/commands/runsvelte.py
django_svelte_married/renderers.py
django_svelte_married/settings.py
django_svelte_married/static/svelte/livereload.js
django_svelte_married/templates/svelte.html
django_svelte_married/templates/svelte_print.html
django_svelte_married/templatetags/__init__.py
django_svelte_married/templatetags/svelte.py
django_svelte_married/tests/test_context_processors.py
django_svelte_married-0.0.8.dist-info/entry_points.txt
django_svelte_married-0.0.8.dist-info/WHEEL
django_svelte_married-0.0.8.dist-info/METADATA
django_svelte_married-0.0.8.dist-info/RECORD
